openalea/__init__.py
openalea/workflow/evaluation.py
openalea/workflow/evaluation_environment.py
openalea/workflow/func_node.py
openalea/workflow/node.py
openalea/workflow/port_graph.py
openalea/workflow/state.py
openalea/workflow/sub_port_graph.py
openalea/workflow/version.py
openalea/workflow/__init__.py
openalea.workflow-0.1.1.dist-info/DESCRIPTION.rst
openalea.workflow-0.1.1.dist-info/METADATA
openalea.workflow-0.1.1.dist-info/metadata.json
openalea.workflow-0.1.1.dist-info/RECORD
openalea.workflow-0.1.1.dist-info/top_level.txt
openalea.workflow-0.1.1.dist-info/WHEEL
