Metadata-Version: 2.0
Name: openalea.workflow
Version: 0.1.1
Summary: Workflow core of openalea
Home-page: UNKNOWN
Author: revesansparole
Author-email: revesansparole@gmail.com
License: mit
Platform: UNKNOWN
Classifier: Development Status :: 2 - Pre-Alpha
Classifier: Intended Audience :: Developers
Classifier: License :: OSI Approved :: BSD License
Classifier: Natural Language :: English
Classifier: Programming Language :: Python
Classifier: Programming Language :: Python :: 2
Classifier: Programming Language :: Python :: 2 :: Only
Classifier: Programming Language :: Python :: 2.7
Requires-Dist: openalea.container
